kiddeelab.py
kiddeelab-0.0.2.dist-info/LICENSE
kiddeelab-0.0.2.dist-info/METADATA
kiddeelab-0.0.2.dist-info/WHEEL
kiddeelab-0.0.2.dist-info/top_level.txt
kiddeelab-0.0.2.dist-info/RECORD
