Metadata-Version: 2.1
Name: kiddeelab
Version: 0.0.2
Summary: Kiddee Lab modules, including a Python Library To Read Data From the Kiddee Joystick and a Python Protocol Abstraction Library For Arduino Firmata - Updated by Kiddee Lab
Home-page: https://github.com/xavjb/kiddeelab
Author: Kiddee Lab
Author-email: kiddeelab2@gmail.com
License: UNKNOWN
Download-URL: https://github.com/xavjb/kiddeelab
Keywords: Firmata,Serial Port,Arduino,Python,Protocol,Python,Kiddee Lab,Joystick,Gamepad
Platform: UNKNOWN
Classifier: Development Status :: 5 - Production/Stable
Classifier: Environment :: Other Environment
Classifier: Intended Audience :: Developers
Classifier: Intended Audience :: Education
Classifier: License :: OSI Approved :: GNU Affero General Public License v3 or later (AGPLv3+)
Classifier: Operating System :: OS Independent
Classifier: Programming Language :: Python :: 3.7
Classifier: Programming Language :: Python :: 3.8
Classifier: Programming Language :: Python :: 3.9
Classifier: Programming Language :: Python :: 3.10
Classifier: Topic :: Software Development :: Libraries :: Python Modules
Requires-Python: >=3.7
License-File: LICENSE
Requires-Dist: pyserial
Requires-Dist: Pillow
Requires-Dist: pygame
